<?xml version="1.0" encoding="utf-8"?>
<odoo>
    <data>
        <record id="hr_termination_type_view_tree" model="ir.ui.view">  
            <field name="name">employee.termination.type.view.tree</field>
            <field name="model">hr.termination.type</field>
            <field name="arch" type="xml">
                <tree string="termination Types" editable="bottom">
                    <field name="name"/>
                </tree>
            </field>
        </record>

        <record id="hr_termination_type_view_form" model="ir.ui.view">
            <field name="name">employee.termination.type.view.form</field>
            <field name="model">hr.termination.type</field>
            <field name="arch" type="xml">
                <form>
                    <group>
                        <group>
                            <field name="name" />
                        </group>
                    </group>
                </form>
            </field>
        </record>

        <record id="hr_termination_type_action" model="ir.actions.act_window">
            <field name="name">Termination Types</field>
            <field name="res_model">hr.termination.type</field>
            <field name="view_mode">tree</field>
        </record>
    </data>
</odoo>
